lazy_find/__init__.py
lazy_find/py.typed
lazy_find-1.0.0.dist-info/METADATA
lazy_find-1.0.0.dist-info/WHEEL
lazy_find-1.0.0.dist-info/licenses/LICENSE
lazy_find-1.0.0.dist-info/licenses/LICENSE_cpython
lazy_find-1.0.0.dist-info/RECORD
