Metadata-Version: 2.4
Name: lazy-find
Version: 1.0.0
Summary: A context manager for lazifying some kinds of imports.
Project-URL: Homepage, https://github.com/Sachaa-Thanasius/lazy-find
Author-email: Sachaa-Thanasius <sachaathanasius@gmail.com>
License-Expression: MIT AND PSF-2.0
License-File: LICENSE
License-File: LICENSE_cpython
Classifier: Intended Audience :: Developers
Classifier: Natural Language :: English
Classifier: Operating System :: OS Independent
Classifier: Programming Language :: Python :: 3
Classifier: Typing :: Typed
Requires-Python: >=3.9
